README.md
setup.py
NiceDecorator/__init__.py
NiceDecorator/decorator.py
NiceDecorator/model.py
NiceDecorator/objective.py
NiceDecorator/separator.py
NiceDecorator/set_param.py
NiceDecorator/timecount.py
NiceDecorator.egg-info/PKG-INFO
NiceDecorator.egg-info/SOURCES.txt
NiceDecorator.egg-info/dependency_links.txt
NiceDecorator.egg-info/top_level.txt
test/test.py