Metadata-Version: 2.1
Name: NiceDecorator
Version: 1.1.2
Summary: An easy and nice decorator package
License: MIT License
Keywords: decorator
Classifier: Programming Language :: Python
Classifier: Programming Language :: Python :: 3.10
Classifier: Programming Language :: Python :: 3.11
Classifier: Programming Language :: Python :: 3.12
Requires-Python: >=3.10, <4
